hdff-0.0.1.data/purelib/hdff/__init__.py
hdff-0.0.1.data/purelib/hdff/_hdff.so
hdff-0.0.1.data/purelib/hdff/hdff.py
hdff-0.0.1.dist-info/LICENSE
hdff-0.0.1.dist-info/METADATA
hdff-0.0.1.dist-info/WHEEL
hdff-0.0.1.dist-info/top_level.txt
hdff-0.0.1.dist-info/RECORD
